{
  "match_info": {
    "match_id": "20250028",
    "date": "2025-10-26",
    "time": "19:35",
    "competition": {
      "name": "中国足球协会超级联赛",
      "season": "2025",
      "round": "Matchweek 28"
    },
    "venue": {
      "name": "待补充",
      "city": "待补充",
      "attendance": 0
    },
    "referee": {
      "name": "待补充",
      "country": "China"
    }
  },
  "teams": {
    "home": {
      "name": "山东泰山",
      "full_name": "山东泰山足球俱乐部",
      "score": 3,
      "score_ht": 0,
      "formation": "4-2-3-1",
      "coach": "凯文·穆斯卡特",
      "captain": "颜骏凌",
      "lineup": [
        {
          "position": "FW",
          "number": 45,
          "name": "莱昂纳多",
          "country": "巴西"
        },
        {
          "position": "MF",
          "number": 47,
          "name": "蒯纪闻",
          "country": "中国"
        },
        {
          "position": "MF",
          "number": 49,
          "name": "李新翔",
          "country": "中国"
        },
        {
          "position": "MF",
          "number": 21,
          "name": "Óscar Melendo",
          "country": "西班牙"
        },
        {
          "position": "DF",
          "number": 11,
          "name": "吕文君",
          "country": "中国"
        },
        {
          "position": "MF",
          "number": 26,
          "name": "刘若钒",
          "country": "中国"
        },
        {
          "position": "MF",
          "number": 27,
          "name": "冯劲",
          "country": "中国"
        },
        {
          "position": "MF",
          "number": 10,
          "name": "维塔尔",
          "country": "巴西"
        },
        {
          "position": "FW",
          "number": 14,
          "name": "李圣龙",
          "country": "中国"
        },
        {
          "position": "MF",
          "number": 22,
          "name": "马修斯·尤萨",
          "country": "巴西"
        },
        {
          "position": "DF",
          "number": 32,
          "name": "李帅",
          "country": "中国"
        },
        {
          "position": "DF",
          "number": 40,
          "name": "吾米提江",
          "country": "中国"
        },
        {
          "position": "DF",
          "number": 5,
          "name": "张琳芃",
          "country": "中国"
        },
        {
          "position": "DF",
          "number": 3,
          "name": "蒋光太",
          "country": "中国"
        },
        {
          "position": "DF",
          "number": 4,
          "name": "王燊超",
          "country": "中国"
        },
        {
          "position": "GK",
          "number": 1,
          "name": "颜骏凌",
          "country": "中国"
        }
      ],
      "substitutes": [
        {
          "position": "FW",
          "number": 45,
          "name": "莱昂纳多",
          "country": "巴西"
        },
        {
          "position": "MF",
          "number": 47,
          "name": "蒯纪闻",
          "country": "中国"
        },
        {
          "position": "MF",
          "number": 21,
          "name": "Óscar Melendo",
          "country": "西班牙"
        },
        {
          "position": "DF",
          "number": 11,
          "name": "吕文君",
          "country": "中国"
        },
        {
          "position": "MF",
          "number": 26,
          "name": "刘若钒",
          "country": "中国"
        },
        {
          "position": "MF",
          "number": 27,
          "name": "冯劲",
          "country": "中国"
        },
        {
          "position": "MF",
          "number": 10,
          "name": "维塔尔",
          "country": "巴西"
        },
        {
          "position": "FW",
          "number": 14,
          "name": "李圣龙",
          "country": "中国"
        },
        {
          "position": "DF",
          "number": 5,
          "name": "张琳芃",
          "country": "中国"
        },
        {
          "position": "DF",
          "number": 3,
          "name": "蒋光太",
          "country": "中国"
        }
      ],
      "substitutions": []
    },
    "away": {
      "name": "上海海港",
      "full_name": "上海海港足球俱乐部",
      "score": 1,
      "score_ht": 0,
      "formation": "4-3-3",
      "coach": "待补充",
      "captain": "待补充",
      "lineup": [
        {
          "position": "FW",
          "number": 19,
          "name": "泽卡",
          "country": "巴西"
        },
        {
          "position": "MF",
          "number": 10,
          "name": "瓦列里·卡扎伊什维利",
          "country": "中国"
        },
        {
          "position": "MF",
          "number": 9,
          "name": "克雷桑",
          "country": "巴西"
        },
        {
          "position": "MF",
          "number": 11,
          "name": "刘洋",
          "country": "中国"
        },
        {
          "position": "DF",
          "number": 17,
          "name": "吴兴涵",
          "country": "中国"
        },
        {
          "position": "MF",
          "number": 8,
          "name": "吉列尔梅·马德鲁加",
          "country": "巴西"
        },
        {
          "position": "MF",
          "number": 35,
          "name": "黄政宇",
          "country": "中国"
        },
        {
          "position": "MF",
          "number": 38,
          "name": "拉斐尔·梅西斯",
          "country": "中国"
        },
        {
          "position": "MF",
          "number": 23,
          "name": "谢文能",
          "country": "中国"
        },
        {
          "position": "DF",
          "number": 5,
          "name": "郑铮",
          "country": "中国"
        },
        {
          "position": "MF",
          "number": 22,
          "name": "李源一",
          "country": "中国"
        },
        {
          "position": "DF",
          "number": 33,
          "name": "高准翼",
          "country": "中国"
        },
        {
          "position": "DF",
          "number": 55,
          "name": "彭啸",
          "country": "中国"
        },
        {
          "position": "GK",
          "number": 14,
          "name": "王大雷",
          "country": "中国"
        }
      ],
      "substitutes": [
        {
          "position": "MF",
          "number": 11,
          "name": "刘洋",
          "country": "中国"
        },
        {
          "position": "DF",
          "number": 17,
          "name": "吴兴涵",
          "country": "中国"
        },
        {
          "position": "MF",
          "number": 38,
          "name": "拉斐尔·梅西斯",
          "country": "中国"
        },
        {
          "position": "MF",
          "number": 23,
          "name": "谢文能",
          "country": "中国"
        },
        {
          "position": "DF",
          "number": 5,
          "name": "郑铮",
          "country": "中国"
        },
        {
          "position": "MF",
          "number": 22,
          "name": "李源一",
          "country": "中国"
        }
      ],
      "substitutions": []
    }
  },
  "events": [
    {
      "minute": null,
      "minute_extra": null,
      "type": "yellow_card",
      "team": "home",
      "player": "待补充",
      "description": "获得黄牌"
    },
    {
      "minute": null,
      "minute_extra": null,
      "type": "yellow_card",
      "team": "home",
      "player": "待补充",
      "description": "获得黄牌"
    },
    {
      "minute": null,
      "minute_extra": null,
      "type": "yellow_card",
      "team": "away",
      "player": "待补充",
      "description": "获得黄牌"
    },
    {
      "minute": null,
      "minute_extra": null,
      "type": "yellow_card",
      "team": "away",
      "player": "待补充",
      "description": "获得黄牌"
    }
  ],
  "statistics": {
    "possession": {
      "home": 50,
      "away": 50
    },
    "shots": {
      "home": 10,
      "away": 10
    },
    "shots_on_target": {
      "home": 5,
      "away": 5
    },
    "saves": {
      "home": 5,
      "away": 5
    },
    "fouls": {
      "home": 10,
      "away": 10
    },
    "corners": {
      "home": 5,
      "away": 5
    },
    "crosses": {
      "home": 20,
      "away": 20
    },
    "interceptions": {
      "home": 10,
      "away": 10
    },
    "offsides": {
      "home": 2,
      "away": 2
    },
    "yellow_cards": {
      "home": 2,
      "away": 2
    },
    "red_cards": {
      "home": 0,
      "away": 0
    }
  },
  "player_stats": {
    "home": [
      {
        "player": "莱昂纳多",
        "goals": 0,
        "assists": 0,
        "shots": 0,
        "shots_on_target": 0,
        "passes": 0,
        "pass_accuracy": "0%",
        "dribbles": 0,
        "dribble_success": 0,
        "fouls_won": 0,
        "fouls_committed": 0,
        "yellow_cards": 0,
        "rating": "7.0"
      },
      {
        "player": "Kuai Jiwen",
        "goals": 0,
        "assists": 0,
        "shots": 0,
        "shots_on_target": 0,
        "passes": 0,
        "pass_accuracy": "0%",
        "dribbles": 0,
        "dribble_success": 0,
        "fouls_won": 0,
        "fouls_committed": 0,
        "yellow_cards": 0,
        "rating": "7.0"
      },
      {
        "player": "Li Xinxiang",
        "goals": 1,
        "assists": 0,
        "shots": 0,
        "shots_on_target": 0,
        "passes": 0,
        "pass_accuracy": "0%",
        "dribbles": 0,
        "dribble_success": 0,
        "fouls_won": 0,
        "fouls_committed": 0,
        "yellow_cards": 0,
        "rating": "7.0"
      },
      {
        "player": "Óscar Melendo",
        "goals": 0,
        "assists": 0,
        "shots": 0,
        "shots_on_target": 0,
        "passes": 0,
        "pass_accuracy": "0%",
        "dribbles": 0,
        "dribble_success": 0,
        "fouls_won": 0,
        "fouls_committed": 0,
        "yellow_cards": 0,
        "rating": "7.0"
      }
    ],
    "away": [
      {
        "player": "Zeca",
        "goals": 0,
        "assists": 2,
        "shots": 0,
        "shots_on_target": 0,
        "passes": 0,
        "pass_accuracy": "0%",
        "dribbles": 0,
        "dribble_success": 0,
        "fouls_won": 0,
        "fouls_committed": 0,
        "yellow_cards": 0,
        "rating": "7.0"
      },
      {
        "player": "Valeri Qazaishvili",
        "goals": 2,
        "assists": 0,
        "shots": 0,
        "shots_on_target": 0,
        "passes": 0,
        "pass_accuracy": "0%",
        "dribbles": 0,
        "dribble_success": 0,
        "fouls_won": 0,
        "fouls_committed": 0,
        "yellow_cards": 0,
        "rating": "7.0"
      },
      {
        "player": "Crysan",
        "goals": 0,
        "assists": 1,
        "shots": 0,
        "shots_on_target": 0,
        "passes": 0,
        "pass_accuracy": "0%",
        "dribbles": 0,
        "dribble_success": 0,
        "fouls_won": 0,
        "fouls_committed": 0,
        "yellow_cards": 0,
        "rating": "7.0"
      },
      {
        "player": "Liu Yang",
        "goals": 1,
        "assists": 0,
        "shots": 0,
        "shots_on_target": 0,
        "passes": 0,
        "pass_accuracy": "0%",
        "dribbles": 0,
        "dribble_success": 0,
        "fouls_won": 0,
        "fouls_committed": 0,
        "yellow_cards": 0,
        "rating": "7.0"
      }
    ]
  },
  "metadata": {
    "source": "manual",
    "url": "",
    "scraped_at": "2025-10-26T19:35:00",
    "version": "3.0"
  }
}