{
  "match_info": {
    "match_id": "9be90ff0",
    "date": "2024-07-12",
    "time": "19:35",
    "competition": {
      "name": "中国足球协会超级联赛",
      "season": "2024",
      "round": "第19轮"
    },
    "venue": {
      "name": "上汽浦东足球场",
      "attendance": 22897
    },
    "referee": {
      "main": "Shunqi Tang",
      "ar1": "Cao Yi",
      "ar2": "Kong Lingda",
      "fourth": "Zhang Yangfan",
      "var": "Gu Chunhan"
    }
  },
  "teams": {
    "home": {
      "name": "上海海港",
      "full_name": "",
      "score": 5,
      "score_ht": 0,
      "formation": "4-2-3-1",
      "coach": "凯文·穆斯卡特",
      "captain": "奥斯卡",
      "lineup": [
        {
          "number": "1",
          "name": "颜骏凌",
          "country": "Unknown"
        },
        {
          "number": "3",
          "name": "蒋光太",
          "country": "Unknown"
        },
        {
          "number": "4",
          "name": "王燊超",
          "country": "Unknown"
        },
        {
          "number": "7",
          "name": "武磊",
          "country": "Unknown"
        },
        {
          "number": "8",
          "name": "奥斯卡",
          "country": "Unknown"
        },
        {
          "number": "9",
          "name": "古斯塔沃",
          "country": "Unknown"
        },
        {
          "number": "10",
          "name": "巴尔加斯",
          "country": "Unknown"
        },
        {
          "number": "13",
          "name": "魏震",
          "country": "Unknown"
        },
        {
          "number": "18",
          "name": "莱奥·奇塔迪尼",
          "country": "Unknown"
        },
        {
          "number": "22",
          "name": "马修斯·尤萨",
          "country": "Unknown"
        },
        {
          "number": "32",
          "name": "李帅",
          "country": "Unknown"
        }
      ],
      "substitutes": [
        {
          "number": "12",
          "name": "陈威",
          "country": "Unknown"
        },
        {
          "number": "2",
          "name": "李昂",
          "country": "Unknown"
        },
        {
          "number": "5",
          "name": "张琳芃",
          "country": "Unknown"
        },
        {
          "number": "11",
          "name": "吕文君",
          "country": "Unknown"
        },
        {
          "number": "14",
          "name": "李圣龙",
          "country": "Unknown"
        },
        {
          "number": "16",
          "name": "徐新",
          "country": "Unknown"
        },
        {
          "number": "23",
          "name": "傅欢",
          "country": "Unknown"
        },
        {
          "number": "27",
          "name": "冯劲",
          "country": "Unknown"
        },
        {
          "number": "31",
          "name": "鲍世蒙",
          "country": "Unknown"
        },
        {
          "number": "33",
          "name": "刘祝润",
          "country": "Unknown"
        },
        {
          "number": "37",
          "name": "陈序煌",
          "country": "Unknown"
        },
        {
          "number": "45",
          "name": "刘小龙",
          "country": "Unknown"
        }
      ]
    },
    "away": {
      "name": "北京国安",
      "full_name": "",
      "score": 1,
      "score_ht": 0,
      "formation": "4-3-3",
      "coach": "Ricardo Soares",
      "captain": "Zhang Xizhe",
      "lineup": [
        {
          "number": "1",
          "name": "Han Jiaqi",
          "country": "Unknown"
        },
        {
          "number": "3",
          "name": "He Yupeng",
          "country": "Unknown"
        },
        {
          "number": "5",
          "name": "Michael Ngadeu-Ngadjui",
          "country": "Unknown"
        },
        {
          "number": "8",
          "name": "Gonçalo Rodrigues",
          "country": "Unknown"
        },
        {
          "number": "10",
          "name": "Zhang Xizhe",
          "country": "Unknown"
        },
        {
          "number": "11",
          "name": "Lin Liangming",
          "country": "Unknown"
        },
        {
          "number": "23",
          "name": "Nico Yennaris",
          "country": "Unknown"
        },
        {
          "number": "24",
          "name": "Samuel Adegbenro",
          "country": "Unknown"
        },
        {
          "number": "27",
          "name": "Wang Gang",
          "country": "Unknown"
        },
        {
          "number": "28",
          "name": "Zhang Chengdong",
          "country": "Unknown"
        },
        {
          "number": "29",
          "name": "Fábio Abreu",
          "country": "Unknown"
        }
      ],
      "substitutes": [
        {
          "number": "25",
          "name": "ZHENG TULUO",
          "country": "Unknown"
        },
        {
          "number": "6",
          "name": "Chi Zhongguo",
          "country": "Unknown"
        },
        {
          "number": "9",
          "name": "Zhang Yuning",
          "country": "Unknown"
        },
        {
          "number": "16",
          "name": "Feng Boxuan",
          "country": "Unknown"
        },
        {
          "number": "17",
          "name": "Yang Liyu",
          "country": "Unknown"
        },
        {
          "number": "18",
          "name": "Fang Hao",
          "country": "Unknown"
        },
        {
          "number": "20",
          "name": "Wang Ziming",
          "country": "Unknown"
        },
        {
          "number": "21",
          "name": "张远",
          "country": "Unknown"
        },
        {
          "number": "22",
          "name": "Yu Dabao",
          "country": "Unknown"
        },
        {
          "number": "26",
          "name": "Bai Yang",
          "country": "Unknown"
        },
        {
          "number": "37",
          "name": "Cao Yongjing",
          "country": "Unknown"
        },
        {
          "number": "38",
          "name": "Ruan Qilong",
          "country": "Unknown"
        }
      ]
    }
  },
  "events": [
    {
      "minute": 13,
      "minute_extra": 0,
      "type": "goal",
      "team": "away",
      "player": "Lin Liangming",
      "player2": "",
      "goal_type": "goal",
      "player_out": "",
      "description": "进球"
    },
    {
      "minute": 16,
      "minute_extra": 0,
      "type": "goal",
      "team": "home",
      "player": "武磊",
      "player2": "",
      "goal_type": "goal",
      "player_out": "",
      "description": "进球"
    },
    {
      "minute": 30,
      "minute_extra": 0,
      "type": "goal",
      "team": "home",
      "player": "古斯塔沃",
      "player2": "",
      "goal_type": "goal",
      "player_out": "",
      "description": "进球"
    },
    {
      "minute": 33,
      "minute_extra": 0,
      "type": "goal",
      "team": "home",
      "player": "古斯塔沃",
      "player2": "",
      "goal_type": "goal",
      "player_out": "",
      "description": "进球"
    },
    {
      "minute": 55,
      "minute_extra": 0,
      "type": "yellow_card",
      "team": "away",
      "player": "He Yupeng",
      "player2": "",
      "goal_type": "",
      "player_out": "",
      "description": "黄牌"
    },
    {
      "minute": 58,
      "minute_extra": 0,
      "type": "goal",
      "team": "home",
      "player": "奥斯卡",
      "player2": "",
      "goal_type": "goal",
      "player_out": "",
      "description": "进球"
    },
    {
      "minute": 60,
      "minute_extra": 0,
      "type": "yellow_card",
      "team": "home",
      "player": "蒋光太",
      "player2": "",
      "goal_type": "",
      "player_out": "",
      "description": "黄牌"
    },
    {
      "minute": 70,
      "minute_extra": 0,
      "type": "substitution",
      "team": "home",
      "player": "傅欢",
      "player2": "王燊超",
      "goal_type": "",
      "player_out": "王燊超",
      "description": "换人"
    },
    {
      "minute": 70,
      "minute_extra": 0,
      "type": "substitution",
      "team": "home",
      "player": "冯劲",
      "player2": "巴尔加斯",
      "goal_type": "",
      "player_out": "巴尔加斯",
      "description": "换人"
    },
    {
      "minute": 71,
      "minute_extra": 0,
      "type": "goal",
      "team": "home",
      "player": "武磊",
      "player2": "",
      "goal_type": "goal",
      "player_out": "",
      "description": "进球"
    },
    {
      "minute": 73,
      "minute_extra": 0,
      "type": "substitution",
      "team": "away",
      "player": "Yang Liyu",
      "player2": "Lin Liangming",
      "goal_type": "",
      "player_out": "Lin Liangming",
      "description": "换人"
    },
    {
      "minute": 73,
      "minute_extra": 0,
      "type": "substitution",
      "team": "away",
      "player": "Chi Zhongguo",
      "player2": "Gonçalo Rodrigues",
      "goal_type": "",
      "player_out": "Gonçalo Rodrigues",
      "description": "换人"
    },
    {
      "minute": 73,
      "minute_extra": 0,
      "type": "substitution",
      "team": "away",
      "player": "张远",
      "player2": "Zhang Xizhe",
      "goal_type": "",
      "player_out": "Zhang Xizhe",
      "description": "换人"
    },
    {
      "minute": 73,
      "minute_extra": 0,
      "type": "substitution",
      "team": "away",
      "player": "Fang Hao",
      "player2": "Samuel Adegbenro",
      "goal_type": "",
      "player_out": "Samuel Adegbenro",
      "description": "换人"
    },
    {
      "minute": 77,
      "minute_extra": 0,
      "type": "substitution",
      "team": "home",
      "player": "徐新",
      "player2": "马修斯·尤萨",
      "goal_type": "",
      "player_out": "马修斯·尤萨",
      "description": "换人"
    },
    {
      "minute": 77,
      "minute_extra": 0,
      "type": "substitution",
      "team": "home",
      "player": "张琳芃",
      "player2": "蒋光太",
      "goal_type": "",
      "player_out": "蒋光太",
      "description": "换人"
    },
    {
      "minute": 77,
      "minute_extra": 0,
      "type": "substitution",
      "team": "away",
      "player": "Wang Ziming",
      "player2": "Fábio Abreu",
      "goal_type": "",
      "player_out": "Fábio Abreu",
      "description": "换人"
    },
    {
      "minute": 79,
      "minute_extra": 0,
      "type": "substitution",
      "team": "home",
      "player": "鲍世蒙",
      "player2": "李帅",
      "goal_type": "",
      "player_out": "李帅",
      "description": "换人"
    }
  ],
  "metadata": {
    "source": "FBref",
    "url": "https://fbref.com/en/matches/9be90ff0/Shanghai-Port-Beijing-Guoan-July-12-2024-Chinese-Super-League",
    "scraped_at": "2026-04-03T22:30:07.857031",
    "statistics_complemented_at": "2026-04-04T18:14:38.591848",
    "statistics_version": "v1.0-full"
  },
  "statistics": {
    "possession": {
      "home": "54%",
      "away": "46%"
    },
    "shots_on_target": {
      "home": "9",
      "away": "3"
    },
    "shots": {
      "home": "31",
      "away": "12"
    },
    "shots_accuracy": {
      "home": "29%",
      "away": "25%"
    },
    "saves": {
      "home": "2 of 3-66%",
      "away": "4 of 9-44%"
    },
    "fouls": {
      "home": "12",
      "away": "11"
    },
    "corners": {
      "home": "8",
      "away": "3"
    },
    "crosses": {
      "home": "20",
      "away": "11"
    },
    "interceptions": {
      "home": "11",
      "away": "12"
    },
    "offsides": {
      "home": "1",
      "away": "2"
    },
    "yellow_cards": {
      "home": 0,
      "away": 0
    },
    "red_cards": {
      "home": 0,
      "away": 0
    }
  }
}